Metadata-Version: 1.0
Name: spmmtb
Version: 2.0
Summary: Simple math module with: add, substract, multiply, divide only, usage: action(first, second)
Home-page: https://github.com/ReGamer45/spmmtb
Author: ReGamer45
Author-email: t.belf2020@gmail.com
License: UNKNOWN
Platform: UNKNOWN
